wagtail_freezer/__init__.py
wagtail_freezer/apps.py
wagtail_freezer/models.py
wagtail_freezer/management/__init__.py
wagtail_freezer/management/commands/__init__.py
wagtail_freezer/management/commands/buildstaticsite.py
wagtail_freezer/test/__init__.py
wagtail_freezer/test/apps.py
wagtail_freezer/test/models.py
wagtail_freezer/test/settings.py
wagtail_freezer/test/urls.py
wagtail_freezer/test/migrations/0001_initial.py
wagtail_freezer/test/migrations/__init__.py
wagtail_freezer/test/static/followed.txt
wagtail_freezer/test/static/homepage.css
wagtail_freezer/test/static/homepage.js
wagtail_freezer/test/templates/wagtail_freezer_test/home_page.html
wagtail_freezer/test/tests/__init__.py
wagtail_freezer/test/tests/test_build.py
wagtail_freezer-0.1.0.dist-info/LICENSE
wagtail_freezer-0.1.0.dist-info/METADATA
wagtail_freezer-0.1.0.dist-info/WHEEL
wagtail_freezer-0.1.0.dist-info/top_level.txt
wagtail_freezer-0.1.0.dist-info/RECORD
