Metadata-Version: 2.1
Name: wagtail-freezer
Version: 0.1.0
Summary: Generates static HTML sites from a Wagtail project
Home-page: 
Author: Matt Westcott
Author-email: matthew@torchbox.com
License: BSD
Classifier: Development Status :: 3 - Alpha
Classifier: Intended Audience :: Developers
Classifier: License :: OSI Approved :: BSD License
Classifier: Operating System :: OS Independent
Classifier: Programming Language :: Python
Classifier: Programming Language :: Python :: 3
Classifier: Programming Language :: Python :: 3.7
Classifier: Programming Language :: Python :: 3.8
Classifier: Programming Language :: Python :: 3.9
Classifier: Programming Language :: Python :: 3.10
Classifier: Framework :: Django
Classifier: Framework :: Django :: 3.2
Classifier: Framework :: Django :: 4.0
Classifier: Framework :: Wagtail
Classifier: Framework :: Wagtail :: 3
License-File: LICENSE
Requires-Dist: Django (<5.0,>=3.0)
Requires-Dist: Wagtail (<4.0,>=3.0)
Requires-Dist: beautifulsoup4 (<5.0,>=4.9)
Provides-Extra: testing
Requires-Dist: dj-database-url (==0.5.0) ; extra == 'testing'
